acidcli/__init__.py
acidcli/__main__.py
acidcli/cli.py
acidcli/configuration.py
acidcli/defaults/pages/static/atom.png
acidcli/defaults/pages/static/capgemini_engineering_logo.svg
acidcli/defaults/pages/static/chain.png
acidcli/defaults/pages/static/cloud.png
acidcli/defaults/pages/static/document.png
acidcli/defaults/pages/static/download.png
acidcli/defaults/pages/static/education.png
acidcli/defaults/pages/static/fingerprint.png
acidcli/defaults/pages/static/gitlab.png
acidcli/defaults/pages/static/graph.png
acidcli/defaults/pages/static/hacker.png
acidcli/defaults/pages/static/home.png
acidcli/defaults/pages/static/jira.png
acidcli/defaults/pages/static/link.png
acidcli/defaults/pages/static/magnifying.png
acidcli/defaults/pages/static/nexus.png
acidcli/defaults/pages/static/question_mark.png
acidcli/defaults/pages/static/server.png
acidcli/defaults/pages/static/servicedesk.png
acidcli/defaults/pages/static/sonarqube.png
acidcli/defaults/pages/static/team.png
acidcli/defaults/pages/templates/base.jinja
acidcli/defaults/pages/templates/capgemini.jinja
acidcli/defaults/pages/templates/page.jinja
acidcli/defaults/pandoc/footer.html
acidcli/defaults/pandoc/images/logo.png
acidcli/defaults/pandoc/images/logo.svg
acidcli/defaults/pandoc/pandoc.css
acidcli/defaults/pandoc/template.latex
acidcli/environment.py
acidcli/exceptions.py
acidcli/facility/__init__.py
acidcli/facility/decorators.py
acidcli/facility/dotcover.py
acidcli/facility/issue_reporter.py
acidcli/facility/junit_transformation.py
acidcli/facility/nunit3_to_junit.ps1
acidcli/facility/nunit3_to_junit.xslt
acidcli/facility/subprocess.py
acidcli/facility/upload.py
acidcli/job.py
acidcli/locale/acidcli.en.yml
acidcli/metamodel/acid.tx
acidcli/postconditions/__init__.py
acidcli/postconditions/exceptions.py
acidcli/postconditions/output.py
acidcli/postconditions/postcondition.py
acidcli/preconditions/__init__.py
acidcli/preconditions/assemblyversion.py
acidcli/preconditions/config.py
acidcli-4.14.0.dist-info/METADATA
acidcli-4.14.0.dist-info/WHEEL
acidcli-4.14.0.dist-info/entry_points.txt
acidcli-4.14.0.dist-info/RECORD
